mapify_cli/__init__.py
mapify_cli/contradiction_detector.py
mapify_cli/entity_extractor.py
mapify_cli/graph_query.py
mapify_cli/relationship_detector.py
mapify_cli/schemas.py
mapify_cli/workflow_logger.py
mapify_cli/workflow_state.py
mapify_cli/templates/settings.hooks.json
mapify_cli/templates/settings.json
mapify_cli/templates/workflow-rules.json
mapify_cli/templates/agents/actor.md
mapify_cli/templates/agents/curator.md
mapify_cli/templates/agents/debate-arbiter.md
mapify_cli/templates/agents/documentation-reviewer.md
mapify_cli/templates/agents/evaluator.md
mapify_cli/templates/agents/monitor.md
mapify_cli/templates/agents/predictor.md
mapify_cli/templates/agents/reflector.md
mapify_cli/templates/agents/research-agent.md
mapify_cli/templates/agents/synthesizer.md
mapify_cli/templates/agents/task-decomposer.md
mapify_cli/templates/commands/map-debate.md
mapify_cli/templates/commands/map-debug.md
mapify_cli/templates/commands/map-efficient.md
mapify_cli/templates/commands/map-fast.md
mapify_cli/templates/commands/map-learn.md
mapify_cli/templates/commands/map-release.md
mapify_cli/templates/commands/map-resume.md
mapify_cli/templates/commands/map-review.md
mapify_cli/templates/hooks/block-dangerous.sh
mapify_cli/templates/hooks/block-secrets.py
mapify_cli/templates/hooks/end-of-turn.sh
mapify_cli/templates/hooks/improve-prompt.py
mapify_cli/templates/map/static-analysis/analyze.sh
mapify_cli/templates/map/static-analysis/handlers/common.sh
mapify_cli/templates/map/static-analysis/handlers/go.sh
mapify_cli/templates/map/static-analysis/handlers/python.sh
mapify_cli/templates/map/static-analysis/handlers/rust.sh
mapify_cli/templates/map/static-analysis/handlers/typescript.sh
mapify_cli/templates/references/decomposition-examples.md
mapify_cli/templates/references/mcp-usage-examples.md
mapify_cli/templates/skills/README.md
mapify_cli/templates/skills/skill-rules.json
mapify_cli/templates/skills/map-cli-reference/SKILL.md
mapify_cli-3.0.0.dist-info/METADATA
mapify_cli-3.0.0.dist-info/WHEEL
mapify_cli-3.0.0.dist-info/entry_points.txt
mapify_cli-3.0.0.dist-info/RECORD
