Metadata-Version: 2.4
Name: mapify-cli
Version: 3.0.0
Summary: MAP Framework installer - Modular Agentic Planner for Claude Code
Project-URL: Homepage, https://github.com/azalio/map-framework
Project-URL: Repository, https://github.com/azalio/map-framework.git
Project-URL: Issues, https://github.com/azalio/map-framework/issues
Author: MAP Framework Contributors
Requires-Python: >=3.11
Requires-Dist: httpx>=0.25.0
Requires-Dist: platformdirs>=4.0.0
Requires-Dist: questionary>=2.0.0
Requires-Dist: readchar>=4.0.0
Requires-Dist: rich>=13.0.0
Requires-Dist: typer>=0.9.0
Provides-Extra: dev
Requires-Dist: black>=23.0.0; extra == 'dev'
Requires-Dist: mypy>=1.0.0; extra == 'dev'
Requires-Dist: pytest-cov>=4.0.0; extra == 'dev'
Requires-Dist: pytest-mock>=3.10.0; extra == 'dev'
Requires-Dist: pytest>=7.0.0; extra == 'dev'
Requires-Dist: ruff>=0.1.0; extra == 'dev'
Provides-Extra: ssl
Requires-Dist: truststore>=0.9.0; extra == 'ssl'
Provides-Extra: test
Requires-Dist: pytest-cov>=4.0.0; extra == 'test'
Requires-Dist: pytest-mock>=3.10.0; extra == 'test'
Requires-Dist: pytest>=7.0.0; extra == 'test'
